qbwrap/__init__.py
qbwrap/action/__init__.py
qbwrap/action/main_action.py
qbwrap/action/run_action.py
qbwrap/action/setup_action.py
qbwrap/dao/__init__.py
qbwrap/dao/argument_parser_dao.py
qbwrap/dao/fields_dao.py
qbwrap/dao/qbwrap_options_dao.py
qbwrap/dao/qbwrap_setup_dao.py
qbwrap/dao/qbwrap_stanza_delegate_dao.py
qbwrap/dao/reference_dao.py
qbwrap/dao/stanza_data_dao.py
qbwrap/dto/__init__.py
qbwrap/dto/bind_dto.py
qbwrap/dto/field_dto.py
qbwrap/dto/reference_dto.py
qbwrap/dto/run_action_options_dto.py
qbwrap/dto/tmpfs_device_dto.py
qbwrap/dto/tmpfs_device_options_dto.py
qbwrap/helper/__init__.py
qbwrap/helper/bwrap_action_helper.py
qbwrap/helper/qbwrap_config_collection_helper.py
qbwrap/helper/qbwrap_config_file_helper.py
qbwrap/helper/qbwrap_config_finder_helper.py
qbwrap/stanza/__init__.py
qbwrap/stanza/base_stanza.py
qbwrap/stanza/core_stanza.py
qbwrap/stanza/emulation_stanza.py
qbwrap/stanza/mount_stanza.py
qbwrap/stanza/setup_stanza.py
qbwrap/stanza/unshare_stanza.py
qbwrap/stanza/user_stanza.py
qbwrap/starter/__init__.py
qbwrap/starter/main.py
qbwrap/util/__init__.py
qbwrap/util/bind_util.py
qbwrap/util/device_util.py
qbwrap/util/file_util.py
qbwrap/util/list_util.py
qbwrap/util/pretty_info_util.py
qbwrap/util/reference_util.py
qbwrap/util/sha_util.py
qbwrap/util/size_util.py
qbwrap/util/user_util.py
qbwrap-1.3.0.dist-info/entry_points.txt
qbwrap-1.3.0.dist-info/WHEEL
qbwrap-1.3.0.dist-info/METADATA
qbwrap-1.3.0.dist-info/RECORD
