Metadata-Version: 2.1
Name: qbwrap
Version: 1.3.0
Summary: This Source Code Form is subject to the terms of the Mozilla Public
Author-email: Maciej Barć <xgqt@riseup.net>
Requires-Python: >=3.9
Classifier: Environment :: Console
Classifier: Operating System :: POSIX
Classifier: Programming Language :: Python :: 3 :: Only
Requires-Dist: tomli
Project-URL: Home, https://gitlab.com/xgqt/xgqt-python-app-qbwrap/
